CHANGES.rst
CONTRIBUTORS.rst
DEVELOP.rst
LICENSE.GPL
LICENSE.rst
MANIFEST.in
Makefile
README.rst
requirements.txt
setup.cfg
setup.py
docs/conf.py
docs/index.rst
src/collective/__init__.py
src/collective.behavior.targetblank.egg-info/PKG-INFO
src/collective.behavior.targetblank.egg-info/SOURCES.txt
src/collective.behavior.targetblank.egg-info/dependency_links.txt
src/collective.behavior.targetblank.egg-info/entry_points.txt
src/collective.behavior.targetblank.egg-info/namespace_packages.txt
src/collective.behavior.targetblank.egg-info/not-zip-safe
src/collective.behavior.targetblank.egg-info/requires.txt
src/collective.behavior.targetblank.egg-info/top_level.txt
src/collective/behavior/__init__.py
src/collective/behavior/targetblank/__init__.py
src/collective/behavior/targetblank/configure.zcml
src/collective/behavior/targetblank/interfaces.py
src/collective/behavior/targetblank/setuphandlers.py
src/collective/behavior/targetblank/testing.py
src/collective/behavior/targetblank/upgrades.py
src/collective/behavior/targetblank/upgrades.zcml
src/collective/behavior/targetblank/behaviors/__init__.py
src/collective/behavior/targetblank/behaviors/configure.zcml
src/collective/behavior/targetblank/behaviors/target_blank.py
src/collective/behavior/targetblank/locales/README.rst
src/collective/behavior/targetblank/locales/__init__.py
src/collective/behavior/targetblank/locales/collective.behavior.targetblank.pot
src/collective/behavior/targetblank/locales/update.py
src/collective/behavior/targetblank/locales/update.sh
src/collective/behavior/targetblank/locales/en/LC_MESSAGES/collective.behavior.targetblank.po
src/collective/behavior/targetblank/locales/fr/LC_MESSAGES/collective.behavior.targetblank.po
src/collective/behavior/targetblank/profiles/default/browserlayer.xml
src/collective/behavior/targetblank/profiles/default/catalog.xml
src/collective/behavior/targetblank/profiles/default/metadata.xml
src/collective/behavior/targetblank/profiles/uninstall/browserlayer.xml
src/collective/behavior/targetblank/profiles/uninstall/catalog.xml
src/collective/behavior/targetblank/tests/__init__.py
src/collective/behavior/targetblank/tests/test_behavior_target_blank.py
src/collective/behavior/targetblank/tests/test_setup.py