Metadata-Version: 2.1
Name: collective.behavior.targetblank
Version: 1.0.1
Summary: A target blank option for Link content type
Home-page: https://pypi.python.org/pypi/collective.behavior.targetblank
Author: Benoit Suttor
Author-email: bsuttor@imio.be
License: GPL version 2
Keywords: Python Plone
Platform: UNKNOWN
Classifier: Environment :: Web Environment
Classifier: Framework :: Plone
Classifier: Framework :: Plone :: Addon
Classifier: Framework :: Plone :: 4.3
Classifier: Programming Language :: Python
Classifier: Programming Language :: Python :: 2.7
Classifier: Operating System :: OS Independent
Classifier: License :: OSI Approved :: GNU General Public License v2 (GPLv2)
Requires-Python: ==2.7
Provides-Extra: test
